{
  "collectionName": "components_menus_menu_items",
  "info": {
    "displayName": "Menu Item",
    "icon": "link",
    "description": ""
  },
  "options": {},
  "attributes": {
    "Title": {
      "type": "string",
      "maxLength": 255,
      "required": true
    },
    "Slug": {
      "type": "string",
      "required": true
    },
    "Target": {
      "type": "enumeration",
      "default": "_blank",
      "enum": [
        "_blank",
        "_self",
        "_parent",
        "_top"
      ]
    },
    "CSS": {
      "type": "string"
    },
    "Type": {
      "type": "enumeration",
      "enum": [
        "normal",
        "icon",
        "mixed",
        "button"
      ]
    },
    "Icon": {
      "type": "media",
      "multiple": false,
      "allowedTypes": [
        "images"
      ]
    }
  }
}
